mildom/__init__.py
mildom/api_request.py
mildom-1.4.4.dist-info/METADATA
mildom-1.4.4.dist-info/WHEEL
mildom-1.4.4.dist-info/top_level.txt
mildom-1.4.4.dist-info/RECORD
