Metadata-Version: 2.1
Name: mildom
Version: 1.4.4
Summary: Unofficial wrapper for mildom api.
Home-page: https://github.com/Alpaca131/mildom_lib
Author: Alpaca131
Author-email: iwa124816@gmail.com
License: MIT
Platform: UNKNOWN
Classifier: Programming Language :: Python :: 3
Classifier: License :: OSI Approved :: MIT License
Classifier: Operating System :: OS Independent
Requires-Python: >=3.7
Requires-Dist: requests (>=2.25.1)
